ament_cmake_core/_dummy.cpython-310-x86_64-linux-gnu.so
ros_ament_cmake_core-2.7.3.data/data/share/ament_cmake_core/local_setup.bash
ros_ament_cmake_core-2.7.3.data/data/share/ament_cmake_core/local_setup.dsv
ros_ament_cmake_core-2.7.3.data/data/share/ament_cmake_core/local_setup.sh
ros_ament_cmake_core-2.7.3.data/data/share/ament_cmake_core/local_setup.zsh
ros_ament_cmake_core-2.7.3.data/data/share/ament_cmake_core/package.dsv
ros_ament_cmake_core-2.7.3.data/data/share/ament_cmake_core/package.xml
ros_ament_cmake_core-2.7.3.data/data/share/ament_cmake_core/cmake/ament_cmake_core-extras.cmake
ros_ament_cmake_core-2.7.3.data/data/share/ament_cmake_core/cmake/ament_cmake_coreConfig-version.cmake
ros_ament_cmake_core-2.7.3.data/data/share/ament_cmake_core/cmake/ament_cmake_coreConfig.cmake
ros_ament_cmake_core-2.7.3.data/data/share/ament_cmake_core/cmake/ament_cmake_environment-extras.cmake
ros_ament_cmake_core-2.7.3.data/data/share/ament_cmake_core/cmake/ament_cmake_environment_hooks-extras.cmake
ros_ament_cmake_core-2.7.3.data/data/share/ament_cmake_core/cmake/ament_cmake_index-extras.cmake
ros_ament_cmake_core-2.7.3.data/data/share/ament_cmake_core/cmake/ament_cmake_package_templates-extras.cmake
ros_ament_cmake_core-2.7.3.data/data/share/ament_cmake_core/cmake/ament_cmake_symlink_install-extras.cmake
ros_ament_cmake_core-2.7.3.data/data/share/ament_cmake_core/cmake/ament_cmake_uninstall_target-extras.cmake
ros_ament_cmake_core-2.7.3.data/data/share/ament_cmake_core/cmake/core/all.cmake
ros_ament_cmake_core-2.7.3.data/data/share/ament_cmake_core/cmake/core/ament_add_default_options.cmake
ros_ament_cmake_core-2.7.3.data/data/share/ament_cmake_core/cmake/core/ament_execute_extensions.cmake
ros_ament_cmake_core-2.7.3.data/data/share/ament_cmake_core/cmake/core/ament_package.cmake
ros_ament_cmake_core-2.7.3.data/data/share/ament_cmake_core/cmake/core/ament_package_xml.cmake
ros_ament_cmake_core-2.7.3.dist-info/METADATA
ros_ament_cmake_core-2.7.3.dist-info/WHEEL
ros_ament_cmake_core-2.7.3.dist-info/top_level.txt
ros_ament_cmake_core-2.7.3.dist-info/RECORD
