Metadata-Version: 2.4
Name: ros-ament-cmake-core
Version: 2.7.3
Summary: Wheel for the ament_cmake_core (ros-ament-cmake-core) ROS 2 package.
Dynamic: description
Dynamic: description-content-type
Dynamic: summary
